{
  "project_info": {
    "project_number": "342988001726",
    "firebase_url": "https://utkansh2020-64e5e.firebaseio.com",
    "project_id": "utkansh2020-64e5e",
    "storage_bucket": "utkansh2020-64e5e.appspot.com"
  },
  "client": [
    {
      "client_info": {
        "mobilesdk_app_id": "1:342988001726:android:5dc55260dedd6f47cca9ef",
        "android_client_info": {
          "package_name": "com.nitj.utkansh20"
        }
      },
      "oauth_client": [
        {
          "client_id": "342988001726-arkqsgp1j9n2e4gkqpajai124la873o2.apps.googleusercontent.com",
          "client_type": 1,
          "android_info": {
            "package_name": "com.nitj.utkansh20",
            "certificate_hash": "c997e7e86f32d4cb26b7c6cf340cb4187c5bb01d"
          }
        },
        {
          "client_id": "342988001726-aroneis38cr5ts0uclpsi31hduk6tebl.apps.googleusercontent.com",
          "client_type": 3
        }
      ],
      "api_key": [
        {
          "current_key": "AIzaSyCv6yhhcDFvLmHO2Pbn0R365qMOx2H2VYg"
        }
      ],
      "services": {
        "appinvite_service": {
          "other_platform_oauth_client": [
            {
              "client_id": "342988001726-aroneis38cr5ts0uclpsi31hduk6tebl.apps.googleusercontent.com",
              "client_type": 3
            }
          ]
        }
      }
    }
  ],
  "configuration_version": "1"
}